pyzytemp/__init__.py
pyzytemp-0.0.1.dist-info/LICENSE
pyzytemp-0.0.1.dist-info/METADATA
pyzytemp-0.0.1.dist-info/WHEEL
pyzytemp-0.0.1.dist-info/top_level.txt
pyzytemp-0.0.1.dist-info/RECORD
