Metadata-Version: 2.1
Name: pyzytemp
Version: 0.0.1
Summary: A library to interface with ZyTemp devices
Home-page: https://github.com/goakley/pyzytemp
Author: Glen Oakley
Author-email: goakley123@gmail.com
License: UNKNOWN
Project-URL: Bug Tracker, https://github.com/goakley/pyzytemp/issues
Platform: UNKNOWN
Classifier: Intended Audience :: Developers
Classifier: Programming Language :: Python :: 3
Classifier: License :: OSI Approved :: Apache Software License
Classifier: Operating System :: OS Independent
Classifier: Topic :: Software Development :: Libraries :: Python Modules
Classifier: Topic :: System :: Hardware :: Universal Serial Bus (USB) :: Human Interface Device (HID)
Requires-Python: >=3.6
License-File: LICENSE
Requires-Dist: hid (>=1.0)
Requires-Dist: pyusb (>=1.0)
